mapper/__init__.py
mapper/casedict.py
mapper/object_mapper.py
mapper/object_mapper_exception.py
object_mapper_312-1.2.0.dist-info/licenses/LICENSE
object_mapper_312-1.2.0.dist-info/licenses/LICENSE.txt
tests/__init__.py
tests/test_object_mapper.py
object_mapper_312-1.2.0.dist-info/METADATA
object_mapper_312-1.2.0.dist-info/WHEEL
object_mapper_312-1.2.0.dist-info/top_level.txt
object_mapper_312-1.2.0.dist-info/RECORD
