Metadata-Version: 2.4
Name: object-mapper-312
Version: 1.2.0
Summary: ObjectMapper is a class for automatic object mapping. It helps you to create objects between                project layers (data layer, service layer, view) in a simple, transparent way.
Home-page: https://github.com/marazt/object-mapper
Author: marazt
Author-email: marazt@gmail.com
License: MIT
Keywords: utils dto object-mapper mapping development
Classifier: Development Status :: 5 - Production/Stable
Classifier: Intended Audience :: Developers
Classifier: Topic :: Software Development :: Build Tools
Classifier: License :: OSI Approved :: MIT License
Classifier: Programming Language :: Python :: 2
Classifier: Programming Language :: Python :: 2.7
Classifier: Programming Language :: Python :: 3
Classifier: Programming Language :: Python :: 3.3
Classifier: Programming Language :: Python :: 3.4
Classifier: Programming Language :: Python :: 3.5
Classifier: Programming Language :: Python :: 3.6
Classifier: Programming Language :: Python :: 3.7
Classifier: Programming Language :: Python :: 3.12
License-File: LICENSE
License-File: LICENSE.txt
Requires-Dist: datetime
Requires-Dist: nose
Provides-Extra: dev
Provides-Extra: test
Requires-Dist: nose; extra == "test"
Dynamic: author
Dynamic: author-email
Dynamic: classifier
Dynamic: description
Dynamic: home-page
Dynamic: keywords
Dynamic: license
Dynamic: license-file
Dynamic: provides-extra
Dynamic: requires-dist
Dynamic: summary
